{
  "flexiTimes" : [ {
    "name" : "StandardDay",
    "date" : "23/08/2018",
    "inOut" : {
      "t1" : {
        "time" : "09:00"
      },
      "t2" : {
        "time" : "16:30"
      }
    },
    "lunch" : {
      "t1" : {
        "time" : "12:00"
      },
      "t2" : {
        "time" : "12:45"
      }
    }
  }, {
    "name" : "StandardDay",
    "date" : "24/08/2018",
    "inOut" : {
      "t1" : {
        "time" : "07:30"
      },
      "t2" : {
        "time" : "16:15"
      }
    },
    "lunch" : {
      "t1" : {
        "time" : "12:00"
      },
      "t2" : {
        "time" : "12:45"
      }
    }
  }, {
    "name" : "AnnualLeave",
    "date" : "27/08/2018"
  }, {
    "name" : "StandardDay",
    "date" : "28/08/2018",
    "inOut" : {
      "t1" : {
        "time" : "07:30"
      },
      "t2" : {
        "time" : "16:35"
      }
    },
    "lunch" : {
      "t1" : {
        "time" : "12:00"
      },
      "t2" : {
        "time" : "12:45"
      }
    }
  }, {
    "name" : "StandardDay",
    "date" : "29/08/2018",
    "inOut" : {
      "t1" : {
        "time" : "07:35"
      },
      "t2" : {
        "time" : "16:20"
      }
    },
    "lunch" : {
      "t1" : {
        "time" : "12:00"
      },
      "t2" : {
        "time" : "12:40"
      }
    }
  }, {
    "name" : "StandardDay",
    "date" : "30/08/2018",
    "inOut" : {
      "t1" : {
        "time" : "07:30"
      },
      "t2" : {
        "time" : "16:25"
      }
    },
    "lunch" : {
      "t1" : {
        "time" : "12:00"
      },
      "t2" : {
        "time" : "12:30"
      }
    }
  }, {
    "name" : "StandardDay",
    "date" : "31/08/2018",
    "inOut" : {
      "t1" : {
        "time" : "07:30"
      },
      "t2" : {
        "time" : "16:15"
      }
    },
    "lunch" : {
      "t1" : {
        "time" : "12:00"
      },
      "t2" : {
        "time" : "12:45"
      }
    }
  }, {
    "name" : "StandardDay",
    "date" : "03/09/2018",
    "inOut" : {
      "t1" : {
        "time" : "07:35"
      },
      "t2" : {
        "time" : "16:35"
      }
    },
    "lunch" : {
      "t1" : {
        "time" : "12:00"
      },
      "t2" : {
        "time" : "12:30"
      }
    }
  }, {
    "name" : "StandardDay",
    "date" : "04/09/2018",
    "inOut" : {
      "t1" : {
        "time" : "07:30"
      },
      "t2" : {
        "time" : "16:25"
      }
    },
    "lunch" : {
      "t1" : {
        "time" : "12:00"
      },
      "t2" : {
        "time" : "12:45"
      }
    }
  }, {
    "name" : "StandardDay",
    "date" : "05/09/2018",
    "inOut" : {
      "t1" : {
        "time" : "07:30"
      },
      "t2" : {
        "time" : "16:55"
      }
    },
    "lunch" : {
      "t1" : {
        "time" : "12:00"
      },
      "t2" : {
        "time" : "12:30"
      }
    }
  }, {
    "name" : "StandardDay",
    "date" : "06/09/2018",
    "inOut" : {
      "t1" : {
        "time" : "07:35"
      },
      "t2" : {
        "time" : "16:25"
      }
    },
    "lunch" : {
      "t1" : {
        "time" : "12:00"
      },
      "t2" : {
        "time" : "12:40"
      }
    }
  }, {
    "name" : "AnnualLeave",
    "date" : "07/09/2018"
  }, {
    "name" : "StandardDay",
    "date" : "10/09/2018",
    "inOut" : {
      "t1" : {
        "time" : "07:30"
      },
      "t2" : {
        "time" : "16:25"
      }
    },
    "lunch" : {
      "t1" : {
        "time" : "12:30"
      },
      "t2" : {
        "time" : "13:15"
      }
    }
  }, {
    "name" : "StandardDay",
    "date" : "11/09/2018",
    "inOut" : {
      "t1" : {
        "time" : "07:30"
      },
      "t2" : {
        "time" : "16:25"
      }
    },
    "lunch" : {
      "t1" : {
        "time" : "13:00"
      },
      "t2" : {
        "time" : "13:30"
      }
    }
  }, {
    "name" : "StandardDay",
    "date" : "12/09/2018",
    "inOut" : {
      "t1" : {
        "time" : "07:30"
      },
      "t2" : {
        "time" : "16:25"
      }
    },
    "lunch" : {
      "t1" : {
        "time" : "14:00"
      },
      "t2" : {
        "time" : "14:35"
      }
    }
  }, {
    "name" : "StandardDay",
    "date" : "13/09/2018",
    "inOut" : {
      "t1" : {
        "time" : "07:30"
      },
      "t2" : {
        "time" : "16:40"
      }
    },
    "lunch" : {
      "t1" : {
        "time" : "13:15"
      },
      "t2" : {
        "time" : "13:50"
      }
    }
  }, {
    "name" : "StandardDay",
    "date" : "14/09/2018",
    "inOut" : {
      "t1" : {
        "time" : "07:35"
      },
      "t2" : {
        "time" : "16:25"
      }
    },
    "lunch" : {
      "t1" : {
        "time" : "13:15"
      },
      "t2" : {
        "time" : "13:45"
      }
    }
  }, {
    "name" : "StandardDay",
    "date" : "17/09/2018",
    "inOut" : {
      "t1" : {
        "time" : "07:35"
      },
      "t2" : {
        "time" : "16:25"
      }
    },
    "lunch" : {
      "t1" : {
        "time" : "12:10"
      },
      "t2" : {
        "time" : "13:10"
      }
    }
  }, {
    "name" : "StandardDay",
    "date" : "18/09/2018",
    "inOut" : {
      "t1" : {
        "time" : "07:30"
      },
      "t2" : {
        "time" : "16:25"
      }
    },
    "lunch" : {
      "t1" : {
        "time" : "12:15"
      },
      "t2" : {
        "time" : "12:45"
      }
    }
  }, {
    "name" : "StandardDay",
    "date" : "19/09/2018",
    "inOut" : {
      "t1" : {
        "time" : "07:30"
      },
      "t2" : {
        "time" : "16:25"
      }
    },
    "lunch" : {
      "t1" : {
        "time" : "12:45"
      },
      "t2" : {
        "time" : "13:30"
      }
    }
  }, {
    "name" : "StandardDay",
    "date" : "20/09/2018",
    "inOut" : {
      "t1" : {
        "time" : "07:15"
      },
      "t2" : {
        "time" : "16:25"
      }
    },
    "lunch" : {
      "t1" : {
        "time" : "13:00"
      },
      "t2" : {
        "time" : "13:30"
      }
    }
  }, {
    "name" : "StandardDay",
    "date" : "21/09/2018",
    "inOut" : {
      "t1" : {
        "time" : "07:10"
      },
      "t2" : {
        "time" : "14:25"
      }
    },
    "lunch" : {
      "t1" : {
        "time" : "12:30"
      },
      "t2" : {
        "time" : "13:00"
      }
    }
  }, {
    "name" : "StandardDay",
    "date" : "24/09/2018",
    "inOut" : {
      "t1" : {
        "time" : "07:15"
      },
      "t2" : {
        "time" : "16:25"
      }
    },
    "lunch" : {
      "t1" : {
        "time" : "12:30"
      },
      "t2" : {
        "time" : "13:00"
      }
    }
  }, {
    "name" : "StandardDay",
    "date" : "25/09/2018",
    "inOut" : {
      "t1" : {
        "time" : "07:10"
      },
      "t2" : {
        "time" : "16:25"
      }
    },
    "lunch" : {
      "t1" : {
        "time" : "12:45"
      },
      "t2" : {
        "time" : "13:15"
      }
    }
  }, {
    "name" : "StandardDay",
    "date" : "26/09/2018",
    "inOut" : {
      "t1" : {
        "time" : "07:15"
      },
      "t2" : {
        "time" : "16:25"
      }
    },
    "lunch" : {
      "t1" : {
        "time" : "13:15"
      },
      "t2" : {
        "time" : "13:50"
      }
    }
  }, {
    "name" : "StandardDay",
    "date" : "27/09/2018",
    "inOut" : {
      "t1" : {
        "time" : "07:15"
      },
      "t2" : {
        "time" : "16:25"
      }
    },
    "lunch" : {
      "t1" : {
        "time" : "12:10"
      },
      "t2" : {
        "time" : "13:20"
      }
    }
  }, {
    "name" : "StandardDay",
    "date" : "28/09/2018",
    "inOut" : {
      "t1" : {
        "time" : "07:10"
      },
      "t2" : {
        "time" : "16:10"
      }
    },
    "lunch" : {
      "t1" : {
        "time" : "12:30"
      },
      "t2" : {
        "time" : "13:00"
      }
    }
  }, {
    "name" : "StandardDay",
    "date" : "01/10/2018",
    "inOut" : {
      "t1" : {
        "time" : "07:10"
      },
      "t2" : {
        "time" : "16:25"
      }
    },
    "lunch" : {
      "t1" : {
        "time" : "12:15"
      },
      "t2" : {
        "time" : "12:45"
      }
    }
  }, {
    "name" : "StandardDay",
    "date" : "02/10/2018",
    "inOut" : {
      "t1" : {
        "time" : "07:15"
      },
      "t2" : {
        "time" : "16:25"
      }
    },
    "lunch" : {
      "t1" : {
        "time" : "12:15"
      },
      "t2" : {
        "time" : "12:45"
      }
    }
  }, {
    "name" : "StandardDay",
    "date" : "03/10/2018",
    "inOut" : {
      "t1" : {
        "time" : "07:15"
      },
      "t2" : {
        "time" : "16:40"
      }
    },
    "lunch" : {
      "t1" : {
        "time" : "12:15"
      },
      "t2" : {
        "time" : "12:45"
      }
    }
  }, {
    "name" : "StandardDay",
    "date" : "04/10/2018",
    "inOut" : {
      "t1" : {
        "time" : "07:15"
      },
      "t2" : {
        "time" : "16:40"
      }
    },
    "lunch" : {
      "t1" : {
        "time" : "12:15"
      },
      "t2" : {
        "time" : "12:45"
      }
    }
  }, {
    "name" : "AnnualLeave",
    "date" : "05/10/2018"
  }, {
    "name" : "StandardDay",
    "date" : "08/10/2018",
    "inOut" : {
      "t1" : {
        "time" : "07:10"
      },
      "t2" : {
        "time" : "16:25"
      }
    },
    "lunch" : {
      "t1" : {
        "time" : "12:30"
      },
      "t2" : {
        "time" : "13:15"
      }
    }
  }, {
    "name" : "StandardDay",
    "date" : "09/10/2018",
    "inOut" : {
      "t1" : {
        "time" : "07:10"
      },
      "t2" : {
        "time" : "16:10"
      }
    },
    "lunch" : {
      "t1" : {
        "time" : "13:15"
      },
      "t2" : {
        "time" : "13:45"
      }
    }
  }, {
    "name" : "StandardDay",
    "date" : "10/10/2018",
    "inOut" : {
      "t1" : {
        "time" : "07:10"
      },
      "t2" : {
        "time" : "16:25"
      }
    },
    "lunch" : {
      "t1" : {
        "time" : "13:15"
      },
      "t2" : {
        "time" : "14:00"
      }
    }
  }, {
    "name" : "StandardDay",
    "date" : "11/10/2018",
    "inOut" : {
      "t1" : {
        "time" : "07:50"
      },
      "t2" : {
        "time" : "16:10"
      }
    },
    "lunch" : {
      "t1" : {
        "time" : "12:30"
      },
      "t2" : {
        "time" : "13:00"
      }
    }
  }, {
    "name" : "StandardDay",
    "date" : "12/10/2018",
    "inOut" : {
      "t1" : {
        "time" : "07:15"
      },
      "t2" : {
        "time" : "15:35"
      }
    },
    "lunch" : {
      "t1" : {
        "time" : "13:15"
      },
      "t2" : {
        "time" : "13:45"
      }
    }
  }, {
    "name" : "StandardDay",
    "date" : "15/10/2018",
    "inOut" : {
      "t1" : {
        "time" : "07:10"
      },
      "t2" : {
        "time" : "16:25"
      }
    },
    "lunch" : {
      "t1" : {
        "time" : "12:30"
      },
      "t2" : {
        "time" : "13:00"
      }
    }
  }, {
    "name" : "StandardDay",
    "date" : "16/10/2018",
    "inOut" : {
      "t1" : {
        "time" : "07:15"
      },
      "t2" : {
        "time" : "16:25"
      }
    },
    "lunch" : {
      "t1" : {
        "time" : "12:45"
      },
      "t2" : {
        "time" : "13:15"
      }
    }
  }, {
    "name" : "StandardDay",
    "date" : "17/10/2018",
    "inOut" : {
      "t1" : {
        "time" : "07:10"
      },
      "t2" : {
        "time" : "16:25"
      }
    },
    "lunch" : {
      "t1" : {
        "time" : "12:45"
      },
      "t2" : {
        "time" : "13:15"
      }
    }
  }, {
    "name" : "StandardDay",
    "date" : "18/10/2018",
    "inOut" : {
      "t1" : {
        "time" : "07:45"
      },
      "t2" : {
        "time" : "16:10"
      }
    },
    "lunch" : {
      "t1" : {
        "time" : "12:30"
      },
      "t2" : {
        "time" : "13:00"
      }
    }
  }, {
    "name" : "StandardDay",
    "date" : "19/10/2018",
    "inOut" : {
      "t1" : {
        "time" : "07:10"
      },
      "t2" : {
        "time" : "16:10"
      }
    },
    "lunch" : {
      "t1" : {
        "time" : "13:20"
      },
      "t2" : {
        "time" : "14:00"
      }
    }
  }, {
    "name" : "StandardDay",
    "date" : "22/10/2018",
    "inOut" : {
      "t1" : {
        "time" : "07:15"
      },
      "t2" : {
        "time" : "16:10"
      }
    },
    "lunch" : {
      "t1" : {
        "time" : "12:30"
      },
      "t2" : {
        "time" : "13:00"
      }
    }
  }, {
    "name" : "StandardDay",
    "date" : "23/10/2018",
    "inOut" : {
      "t1" : {
        "time" : "07:15"
      },
      "t2" : {
        "time" : "16:25"
      }
    },
    "lunch" : {
      "t1" : {
        "time" : "12:30"
      },
      "t2" : {
        "time" : "13:15"
      }
    }
  }, {
    "name" : "StandardDay",
    "date" : "24/10/2018",
    "inOut" : {
      "t1" : {
        "time" : "07:15"
      },
      "t2" : {
        "time" : "16:25"
      }
    },
    "lunch" : {
      "t1" : {
        "time" : "12:30"
      },
      "t2" : {
        "time" : "13:00"
      }
    }
  }, {
    "name" : "StandardDay",
    "date" : "25/10/2018",
    "inOut" : {
      "t1" : {
        "time" : "07:10"
      },
      "t2" : {
        "time" : "15:10"
      }
    },
    "lunch" : {
      "t1" : {
        "time" : "12:30"
      },
      "t2" : {
        "time" : "13:30"
      }
    }
  }, {
    "name" : "StandardDay",
    "date" : "26/10/2018",
    "inOut" : {
      "t1" : {
        "time" : "07:15"
      },
      "t2" : {
        "time" : "15:35"
      }
    },
    "lunch" : {
      "t1" : {
        "time" : "12:45"
      },
      "t2" : {
        "time" : "13:15"
      }
    }
  }, {
    "name" : "StandardDay",
    "date" : "29/10/2018",
    "inOut" : {
      "t1" : {
        "time" : "07:10"
      },
      "t2" : {
        "time" : "16:25"
      }
    },
    "lunch" : {
      "t1" : {
        "time" : "13:00"
      },
      "t2" : {
        "time" : "13:30"
      }
    }
  }, {
    "name" : "StandardDay",
    "date" : "30/10/2018",
    "inOut" : {
      "t1" : {
        "time" : "07:10"
      },
      "t2" : {
        "time" : "16:10"
      }
    },
    "lunch" : {
      "t1" : {
        "time" : "13:15"
      },
      "t2" : {
        "time" : "13:45"
      }
    }
  }, {
    "name" : "StandardDay",
    "date" : "31/10/2018",
    "inOut" : {
      "t1" : {
        "time" : "07:15"
      },
      "t2" : {
        "time" : "16:25"
      }
    },
    "lunch" : {
      "t1" : {
        "time" : "13:00"
      },
      "t2" : {
        "time" : "13:30"
      }
    }
  }, {
    "name" : "StandardDay",
    "date" : "01/11/2018",
    "inOut" : {
      "t1" : {
        "time" : "07:40"
      },
      "t2" : {
        "time" : "16:00"
      }
    },
    "lunch" : {
      "t1" : {
        "time" : "13:00"
      },
      "t2" : {
        "time" : "13:30"
      }
    }
  }, {
    "name" : "StandardDay",
    "date" : "02/11/2018",
    "inOut" : {
      "t1" : {
        "time" : "07:10"
      },
      "t2" : {
        "time" : "15:10"
      }
    },
    "lunch" : {
      "t1" : {
        "time" : "13:00"
      },
      "t2" : {
        "time" : "13:30"
      }
    }
  }, {
    "name" : "StandardDay",
    "date" : "05/11/2018",
    "inOut" : {
      "t1" : {
        "time" : "07:10"
      },
      "t2" : {
        "time" : "16:25"
      }
    },
    "lunch" : {
      "t1" : {
        "time" : "12:45"
      },
      "t2" : {
        "time" : "13:15"
      }
    }
  }, {
    "name" : "StandardDay",
    "date" : "06/11/2018",
    "inOut" : {
      "t1" : {
        "time" : "07:15"
      },
      "t2" : {
        "time" : "16:25"
      }
    },
    "lunch" : {
      "t1" : {
        "time" : "13:15"
      },
      "t2" : {
        "time" : "13:45"
      }
    }
  }, {
    "name" : "StandardDay",
    "date" : "07/11/2018",
    "inOut" : {
      "t1" : {
        "time" : "07:15"
      },
      "t2" : {
        "time" : "16:25"
      }
    },
    "lunch" : {
      "t1" : {
        "time" : "12:30"
      },
      "t2" : {
        "time" : "13:00"
      }
    }
  }, {
    "name" : "StandardDay",
    "date" : "08/11/2018",
    "inOut" : {
      "t1" : {
        "time" : "07:15"
      },
      "t2" : {
        "time" : "15:10"
      }
    },
    "lunch" : {
      "t1" : {
        "time" : "12:30"
      },
      "t2" : {
        "time" : "13:00"
      }
    }
  }, {
    "name" : "StandardDay",
    "date" : "09/11/2018",
    "inOut" : {
      "t1" : {
        "time" : "07:10"
      },
      "t2" : {
        "time" : "16:40"
      }
    },
    "lunch" : {
      "t1" : {
        "time" : "13:10"
      },
      "t2" : {
        "time" : "13:40"
      }
    }
  }, {
    "name" : "StandardDay",
    "date" : "12/11/2018",
    "inOut" : {
      "t1" : {
        "time" : "07:15"
      },
      "t2" : {
        "time" : "16:25"
      }
    },
    "lunch" : {
      "t1" : {
        "time" : "12:45"
      },
      "t2" : {
        "time" : "13:15"
      }
    }
  }, {
    "name" : "StandardDay",
    "date" : "13/11/2018",
    "inOut" : {
      "t1" : {
        "time" : "07:15"
      },
      "t2" : {
        "time" : "16:25"
      }
    },
    "lunch" : {
      "t1" : {
        "time" : "12:45"
      },
      "t2" : {
        "time" : "13:15"
      }
    }
  }, {
    "name" : "StandardDay",
    "date" : "14/11/2018",
    "inOut" : {
      "t1" : {
        "time" : "07:50"
      },
      "t2" : {
        "time" : "16:00"
      }
    },
    "lunch" : {
      "t1" : {
        "time" : "13:00"
      },
      "t2" : {
        "time" : "13:30"
      }
    }
  }, {
    "name" : "StandardDay",
    "date" : "15/11/2018",
    "inOut" : {
      "t1" : {
        "time" : "07:15"
      },
      "t2" : {
        "time" : "15:10"
      }
    },
    "lunch" : {
      "t1" : {
        "time" : "13:00"
      },
      "t2" : {
        "time" : "13:30"
      }
    }
  }, {
    "name" : "StandardDay",
    "date" : "16/11/2018",
    "inOut" : {
      "t1" : {
        "time" : "07:15"
      },
      "t2" : {
        "time" : "17:00"
      }
    },
    "lunch" : {
      "t1" : {
        "time" : "13:00"
      },
      "t2" : {
        "time" : "13:30"
      }
    }
  }, {
    "name" : "StandardDay",
    "date" : "19/11/2018",
    "inOut" : {
      "t1" : {
        "time" : "09:15"
      },
      "t2" : {
        "time" : "16:25"
      }
    },
    "lunch" : {
      "t1" : {
        "time" : "12:30"
      },
      "t2" : {
        "time" : "13:00"
      }
    }
  }, {
    "name" : "StandardDay",
    "date" : "20/11/2018",
    "inOut" : {
      "t1" : {
        "time" : "07:15"
      },
      "t2" : {
        "time" : "16:25"
      }
    },
    "lunch" : {
      "t1" : {
        "time" : "13:00"
      },
      "t2" : {
        "time" : "13:30"
      }
    }
  }, {
    "name" : "StandardDay",
    "date" : "21/11/2018",
    "inOut" : {
      "t1" : {
        "time" : "07:15"
      },
      "t2" : {
        "time" : "16:15"
      }
    },
    "lunch" : {
      "t1" : {
        "time" : "13:00"
      },
      "t2" : {
        "time" : "13:30"
      }
    }
  }, {
    "name" : "StandardDay",
    "date" : "22/11/2018",
    "inOut" : {
      "t1" : {
        "time" : "07:15"
      },
      "t2" : {
        "time" : "16:15"
      }
    },
    "lunch" : {
      "t1" : {
        "time" : "12:45"
      },
      "t2" : {
        "time" : "13:15"
      }
    }
  }, {
    "name" : "StandardDay",
    "date" : "23/11/2018",
    "inOut" : {
      "t1" : {
        "time" : "07:20"
      },
      "t2" : {
        "time" : "16:00"
      }
    },
    "lunch" : {
      "t1" : {
        "time" : "12:45"
      },
      "t2" : {
        "time" : "13:15"
      }
    }
  }, {
    "name" : "StandardDay",
    "date" : "26/11/2018",
    "inOut" : {
      "t1" : {
        "time" : "07:15"
      },
      "t2" : {
        "time" : "16:25"
      }
    },
    "lunch" : {
      "t1" : {
        "time" : "13:00"
      },
      "t2" : {
        "time" : "13:30"
      }
    }
  }, {
    "name" : "StandardDay",
    "date" : "27/11/2018",
    "inOut" : {
      "t1" : {
        "time" : "07:15"
      },
      "t2" : {
        "time" : "16:25"
      }
    },
    "lunch" : {
      "t1" : {
        "time" : "13:15"
      },
      "t2" : {
        "time" : "13:45"
      }
    }
  }, {
    "name" : "StandardDay",
    "date" : "28/11/2018",
    "inOut" : {
      "t1" : {
        "time" : "07:15"
      },
      "t2" : {
        "time" : "16:25"
      }
    },
    "lunch" : {
      "t1" : {
        "time" : "13:00"
      },
      "t2" : {
        "time" : "13:30"
      }
    }
  }, {
    "name" : "StandardDay",
    "date" : "29/11/2018",
    "inOut" : {
      "t1" : {
        "time" : "07:15"
      },
      "t2" : {
        "time" : "16:25"
      }
    },
    "lunch" : {
      "t1" : {
        "time" : "12:15"
      },
      "t2" : {
        "time" : "13:45"
      }
    }
  }, {
    "name" : "StandardDay",
    "date" : "30/11/2018",
    "inOut" : {
      "t1" : {
        "time" : "07:10"
      },
      "t2" : {
        "time" : "15:00"
      }
    },
    "lunch" : {
      "t1" : {
        "time" : "13:00"
      },
      "t2" : {
        "time" : "13:30"
      }
    }
  }, {
    "name" : "StandardDay",
    "date" : "03/12/2018",
    "inOut" : {
      "t1" : {
        "time" : "07:15"
      },
      "t2" : {
        "time" : "16:25"
      }
    },
    "lunch" : {
      "t1" : {
        "time" : "12:45"
      },
      "t2" : {
        "time" : "13:15"
      }
    }
  }, {
    "name" : "StandardDay",
    "date" : "04/12/2018",
    "inOut" : {
      "t1" : {
        "time" : "07:15"
      },
      "t2" : {
        "time" : "16:10"
      }
    },
    "lunch" : {
      "t1" : {
        "time" : "12:30"
      },
      "t2" : {
        "time" : "13:00"
      }
    }
  }, {
    "name" : "StandardDay",
    "date" : "05/12/2018",
    "inOut" : {
      "t1" : {
        "time" : "07:15"
      },
      "t2" : {
        "time" : "16:25"
      }
    },
    "lunch" : {
      "t1" : {
        "time" : "12:30"
      },
      "t2" : {
        "time" : "13:00"
      }
    }
  }, {
    "name" : "StandardDay",
    "date" : "06/12/2018",
    "inOut" : {
      "t1" : {
        "time" : "07:15"
      },
      "t2" : {
        "time" : "15:10"
      }
    },
    "lunch" : {
      "t1" : {
        "time" : "12:45"
      },
      "t2" : {
        "time" : "13:15"
      }
    }
  }, {
    "name" : "StandardDay",
    "date" : "07/12/2018",
    "inOut" : {
      "t1" : {
        "time" : "07:10"
      },
      "t2" : {
        "time" : "16:40"
      }
    },
    "lunch" : {
      "t1" : {
        "time" : "13:00"
      },
      "t2" : {
        "time" : "14:00"
      }
    }
  }, {
    "name" : "AnnualLeave",
    "date" : "10/12/2018"
  }, {
    "name" : "StandardDay",
    "date" : "11/12/2018",
    "inOut" : {
      "t1" : {
        "time" : "07:20"
      },
      "t2" : {
        "time" : "16:25"
      }
    },
    "lunch" : {
      "t1" : {
        "time" : "12:45"
      },
      "t2" : {
        "time" : "13:15"
      }
    }
  }, {
    "name" : "StandardDay",
    "date" : "12/12/2018",
    "inOut" : {
      "t1" : {
        "time" : "07:15"
      },
      "t2" : {
        "time" : "15:25"
      }
    },
    "lunch" : {
      "t1" : {
        "time" : "12:45"
      },
      "t2" : {
        "time" : "13:15"
      }
    }
  }, {
    "name" : "StandardDay",
    "date" : "13/12/2018",
    "inOut" : {
      "t1" : {
        "time" : "07:20"
      },
      "t2" : {
        "time" : "15:25"
      }
    },
    "lunch" : {
      "t1" : {
        "time" : "12:15"
      },
      "t2" : {
        "time" : "12:45"
      }
    }
  }, {
    "name" : "StandardDay",
    "date" : "14/12/2018",
    "inOut" : {
      "t1" : {
        "time" : "07:20"
      },
      "t2" : {
        "time" : "15:25"
      }
    },
    "lunch" : {
      "t1" : {
        "time" : "13:15"
      },
      "t2" : {
        "time" : "13:45"
      }
    }
  }, {
    "name" : "StandardDay",
    "date" : "17/12/2018",
    "inOut" : {
      "t1" : {
        "time" : "07:15"
      },
      "t2" : {
        "time" : "13:55"
      }
    },
    "lunch" : {
      "t1" : {
        "time" : "12:30"
      },
      "t2" : {
        "time" : "13:00"
      }
    }
  }, {
    "name" : "StandardDay",
    "date" : "18/12/2018",
    "inOut" : {
      "t1" : {
        "time" : "07:20"
      },
      "t2" : {
        "time" : "16:10"
      }
    },
    "lunch" : {
      "t1" : {
        "time" : "12:30"
      },
      "t2" : {
        "time" : "13:00"
      }
    }
  }, {
    "name" : "HalfDay",
    "date" : "19/12/2018",
    "inOut" : {
      "t1" : {
        "time" : "07:35"
      },
      "t2" : {
        "time" : "11:20"
      }
    }
  }, {
    "name" : "UnknownDayType",
    "date" : "20/12/2018"
  } ]
}